alu_projects/rtl/n_bit_alu.v
module n_bit_alu #(parameter N = 4)
(
    input  [N-1:0] a,
    input  [N-1:0] b,
    input  [2:0]   sel,

    output [N-1:0] y,
    output          carry,
    output          overflow,
    output          negative,
    output          zero
);

    //==================================================
    // ALU Operation Codes
    //==================================================
    localparam ALU_ADD         = 3'b000;
    localparam ALU_SUB         = 3'b001;
    localparam ALU_OR          = 3'b010;
    localparam ALU_AND         = 3'b011;
    localparam ALU_XOR         = 3'b100;
    localparam ALU_LEFT_SHIFT  = 3'b101;
    localparam ALU_RIGHT_SHIFT = 3'b110;
    localparam ALU_PASS        = 3'b111;

    //==================================================
    // Internal Result Wires
    //==================================================
    wire [N:0]   add_result;
    wire [N:0]   sub_result;
    wire [N-1:0] and_result;
    wire [N-1:0] or_result;
    wire [N-1:0] xor_result;
    wire [N-1:0] left_shift;
    wire [N-1:0] right_shift;
    wire [N-1:0] pass_result;

    //==================================================
    // ALU Operations
    //==================================================
    assign add_result   = {1'b0, a} + {1'b0, b};
    assign sub_result   = {1'b0, a} - {1'b0, b};

    assign and_result   = a & b;
    assign or_result    = a | b;
    assign xor_result   = a ^ b;

    assign left_shift   = a << 1;
    assign right_shift  = a >> 1;

    assign pass_result  = a;

    //==================================================
    // Output Multiplexer
    //==================================================
    assign y =
        (sel == ALU_ADD)         ? add_result[N-1:0] :
        (sel == ALU_SUB)         ? sub_result[N-1:0] :
        (sel == ALU_OR)          ? or_result :
        (sel == ALU_AND)         ? and_result :
        (sel == ALU_XOR)         ? xor_result :
        (sel == ALU_LEFT_SHIFT)  ? left_shift :
        (sel == ALU_RIGHT_SHIFT) ? right_shift :
        (sel == ALU_PASS)        ? pass_result :
                                   {N{1'b0}};

    //==================================================
    // Status Flags
    //==================================================
    assign carry =
        (sel == ALU_ADD) ? add_result[N] :
        (sel == ALU_SUB) ? sub_result[N] :
                           1'b0;

    assign zero     = (y == 0);
    assign negative = y[N-1];

    assign overflow =
        (sel == ALU_ADD) ?
            (~(a[N-1] ^ b[N-1])) & (a[N-1] ^ y[N-1]) :

        (sel == ALU_SUB) ?
            ((a[N-1] ^ b[N-1])) & (a[N-1] ^ y[N-1]) :

        1'b0;

endmodule

alu_projects/tb/n_bit_alu_tb.v
`timescale 1ns/1ps

module n_bit_alu_tb;

    //==================================================
    // Parameters
    //==================================================
    localparam N = 4;

    //==================================================
    // ALU Operation Codes
    //==================================================
    localparam ALU_ADD         = 3'b000;
    localparam ALU_SUB         = 3'b001;
    localparam ALU_OR          = 3'b010;
    localparam ALU_AND         = 3'b011;
    localparam ALU_XOR         = 3'b100;
    localparam ALU_LEFT_SHIFT  = 3'b101;
    localparam ALU_RIGHT_SHIFT = 3'b110;
    localparam ALU_PASS        = 3'b111;

    //==================================================
    // Testbench Signals
    //==================================================
    reg  [N-1:0] a;
    reg  [N-1:0] b;
    reg  [2:0]   sel;

    wire [N-1:0] y;
    wire carry;
    wire zero;
    wire negative;
    wire overflow;

    //==================================================
    // DUT
    //==================================================
    n_bit_alu #(N) dut (
        .a(a),
        .b(b),
        .sel(sel),
        .y(y),
        .carry(carry),
        .zero(zero),
        .negative(negative),
        .overflow(overflow)
    );

    //==================================================
    // Golden Model Outputs
    //==================================================
    reg [N-1:0] exp_y;
    reg         exp_carry;
    reg         exp_zero;
    reg         exp_negative;
    reg         exp_overflow;

    integer errors = 0;

    //==================================================
    // Golden Reference Model
    //==================================================
    task compute_expected;
    begin

        exp_y         = 0;
        exp_carry     = 0;
        exp_zero      = 0;
        exp_negative  = 0;
        exp_overflow  = 0;

        case(sel)

            ALU_ADD: begin
                {exp_carry, exp_y} = a + b;
                exp_overflow =
                    (~(a[N-1] ^ b[N-1])) &
                    (a[N-1] ^ exp_y[N-1]);
            end

            ALU_SUB: begin
                {exp_carry, exp_y} = a - b;
                exp_overflow =
                    (a[N-1] ^ b[N-1]) &
                    (a[N-1] ^ exp_y[N-1]);
            end

            ALU_OR:
                exp_y = a | b;

            ALU_AND:
                exp_y = a & b;

            ALU_XOR:
                exp_y = a ^ b;

            ALU_LEFT_SHIFT:
                exp_y = a << 1;

            ALU_RIGHT_SHIFT:
                exp_y = a >> 1;

            ALU_PASS:
                exp_y = a;

            default:
                exp_y = {N{1'bx}};

        endcase

        exp_zero     = (exp_y == 0);
        exp_negative = exp_y[N-1];

    end
    endtask

    //==================================================
    // Checker
    //==================================================
    task check_results;
    begin

        if (y !== exp_y) begin
            $display(
                "Y ERROR: sel=%b a=%b b=%b Expected=%b Got=%b",
                sel, a, b, exp_y, y
            );
            errors = errors + 1;
        end

        if (carry !== exp_carry) begin
            $display(
                "CARRY ERROR: sel=%b a=%b b=%b Expected=%b Got=%b",
                sel, a, b, exp_carry, carry
            );
            errors = errors + 1;
        end

        if (zero !== exp_zero) begin
            $display(
                "ZERO ERROR: sel=%b a=%b b=%b Expected=%b Got=%b",
                sel, a, b, exp_zero, zero
            );
            errors = errors + 1;
        end

        if (negative !== exp_negative) begin
            $display(
                "NEGATIVE ERROR: sel=%b a=%b b=%b Expected=%b Got=%b",
                sel, a, b, exp_negative, negative
            );
            errors = errors + 1;
        end

        if (overflow !== exp_overflow) begin
            $display(
                "OVERFLOW ERROR: sel=%b a=%b b=%b Expected=%b Got=%b",
                sel, a, b, exp_overflow, overflow
            );
            errors = errors + 1;
        end

    end
    endtask

    //==================================================
    // Run One Test
    //==================================================
    task run_test;

        input [N-1:0] test_a;
        input [N-1:0] test_b;
        input [2:0]   test_sel;

    begin

        a   = test_a;
        b   = test_b;
        sel = test_sel;

        compute_expected();

        #1;

        check_results();

    end
    endtask

    //==================================================
    // Test Sequence
    //==================================================
    initial begin

        $display("-------------------------------------");
        $display(" Starting ALU Directed Tests");
        $display("-------------------------------------");

        // ADD
        run_test(4'd3, 4'd2, ALU_ADD);

        // SUB
        run_test(4'd7, 4'd2, ALU_SUB);

        // OR
        run_test(4'b1010, 4'b0101, ALU_OR);

        // AND
        run_test(4'b1010, 4'b1100, ALU_AND);

        // XOR
        run_test(4'b1010, 4'b1100, ALU_XOR);

        // LEFT SHIFT
        run_test(4'b0011, 4'b0000, ALU_LEFT_SHIFT);

        // RIGHT SHIFT
        run_test(4'b1000, 4'b0000, ALU_RIGHT_SHIFT);

        // PASS
        run_test(4'b1110, 4'b0000, ALU_PASS);

        $display("-------------------------------------");
        $display(" Starting Random Tests");
        $display("-------------------------------------");

        repeat(1000) begin
            run_test(
                $random,
                $random,
                $random % 8
            );
        end

        if(errors == 0)
            $display("\nTEST PASSED ✔");

        else
            $display("\nTEST FAILED ❌ Errors = %0d", errors);

        $finish;

    end

    //==================================================
    // Waveform Dump
    //==================================================
    initial begin
        $dumpfile("wave/n_bit_alu_wave.vcd");
        $dumpvars(0, n_bit_alu_tb);
    end

endmodule

alu_projects/wave/n_bit_alu_wave.vcd
$date
	Thu Jul 02 06:04:23 2026
$end
$version
	Icarus Verilog
$end
$timescale
	1ps
$end
$scope module n_bit_alu_tb $end
$var wire 1 ! carry $end
$var wire 1 " negative $end
$var wire 1 # overflow $end
$var wire 4 $ y [3:0] $end
$var wire 1 % zero $end
$var reg 4 & a [3:0] $end
$var reg 4 ' b [3:0] $end
$var integer 32 ( errors [31:0] $end
$var reg 1 ) exp_carry $end
$var reg 1 * exp_negative $end
$var reg 1 + exp_overflow $end
$var reg 4 , exp_y [3:0] $end
$var reg 1 - exp_zero $end
$var reg 3 . sel [2:0] $end
$scope module dut $end
$var wire 4 / a [3:0] $end
$var wire 5 0 add_result [4:0] $end
$var wire 4 1 and_result [3:0] $end
$var wire 4 2 b [3:0] $end
$var wire 1 ! carry $end
$var wire 4 3 left_shift [3:0] $end
$var wire 1 " negative $end
$var wire 4 4 or_result [3:0] $end
$var wire 1 # overflow $end
$var wire 4 5 pass_result [3:0] $end
$var wire 4 6 right_shift [3:0] $end
$var wire 3 7 sel [2:0] $end
$var wire 5 8 sub_result [4:0] $end
$var wire 4 9 xor_result [3:0] $end
$var wire 4 : y [3:0] $end
$var wire 1 % zero $end
$upscope $end
$scope task check_results $end
$upscope $end
$scope task compute_expected $end
$upscope $end
$scope task run_test $end
$var reg 4 ; test_a [3:0] $end
$var reg 4 < test_b [3:0] $end
$var reg 3 = test_sel [2:0] $end
$upscope $end
$upscope $end
$enddefinitions $end
#0
$dumpvars
b0 =
b10 <
b11 ;
b101 :
b1 9
b1 8
b0 7
b1 6
b11 5
b11 4
b110 3
b10 2
b10 1
b101 0
b11 /
b0 .
0-
b101 ,
0+
0*
0)
b0 (
b10 '
b11 &
0%
b101 $
0#
0"
0!
$end
#1000
b111 4
b101 9
b1110 3
b11 6
b101 ,
b1 .
b1 7
b111 &
b111 5
b111 /
b1001 0
b101 8
b1 =
b111 ;
#2000
1"
b1111 $
b1111 :
b0 1
b1111 4
b1111 9
b100 3
b101 6
1*
b1111 ,
b10 .
b10 7
b101 '
b101 2
b1010 &
b1010 5
b1010 /
b1111 0
b101 8
b10 =
b101 <
b1010 ;
#3000
b1000 $
b1000 :
b1000 1
b1110 4
b110 9
1*
b1000 ,
b11 .
b11 7
b1100 '
b1100 2
b10110 0
b11110 8
b11 =
b1100 <
#4000
0"
b110 $
b110 :
0*
b110 ,
b100 .
b100 7
b100 =
#5000
b0 1
b11 4
b11 9
b110 3
b1 6
b110 ,
b101 .
b101 7
b0 '
b0 2
b11 &
b11 5
b11 /
b11 0
b11 8
b101 =
b0 <
b11 ;
#6000
b100 $
b100 :
b1000 4
b1000 9
b0 3
b100 6
b100 ,
b110 .
b110 7
b1000 &
b1000 5
b1000 /
b1000 0
b1000 8
b110 =
b1000 ;
#7000
1"
b1110 $
b1110 :
b1110 4
b1110 9
b1100 3
b111 6
1*
b1110 ,
b111 .
b111 7
b1110 &
b1110 5
b1110 /
b1110 0
b1110 8
b111 =
b1110 ;
#8000
0"
b11 $
b11 :
b101 4
b101 9
b1000 3
b10 6
0*
b11 ,
b1 .
b1 7
b1 '
b1 2
b100 &
b100 5
b100 /
b101 0
b11 8
b1 =
b1 <
b100 ;
#9000
0%
b110 $
b110 :
b1 1
b1111 4
b1110 9
b110 3
b1 6
b110 ,
b101 .
b101 7
b1101 '
b1101 2
b11 &
b11 5
b11 /
b10000 0
b10110 8
b101 =
b1101 <
b11 ;
#10000
b11 $
b11 :
b0 1
b111 4
b111 9
b1010 3
b10 6
b11 ,
b1 .
b1 7
b10 '
b10 2
b101 &
b101 5
b101 /
b111 0
b11 8
b1 =
b10 <
b101 ;
#11000
1"
0%
b1010 $
b1010 :
b100 1
b1111 4
b1011 9
b110 6
1*
b1010 ,
b101 .
b101 7
b110 '
b110 2
b1101 &
b1101 5
b1101 /
b10011 0
b111 8
b101 =
b110 <
b1101 ;
#12000
0"
b1 $
b1 :
b1100 1
b1101 4
b1 9
0*
b1 ,
b1 .
b1 7
b1100 '
b1100 2
b11001 0
b1 8
b1 =
b1100 <
#13000
b111 $
b111 :
b100 1
b111 4
b11 9
b1100 3
b11 6
b111 ,
b10 .
b10 7
b101 '
b101 2
b110 &
b110 5
b110 /
b1011 0
b1 8
b10 =
b101 <
b110 ;
#14000
b101 1
b10 9
b1010 3
b10 6
b111 ,
b111 '
b111 2
b101 &
b101 5
b101 /
b1100 0
b11110 8
b111 <
b101 ;
#15000
0%
b111 $
b111 :
b10 1
b1111 4
b1101 9
b1110 3
b111 6
b111 ,
b110 .
b110 7
b10 '
b10 2
b1111 &
b1111 5
b1111 /
b10001 0
b1101 8
b110 =
b10 <
b1111 ;
#16000
1"
b1101 $
b1101 :
b0 1
b1101 4
b0 3
b100 6
1*
b1101 ,
b100 .
b100 7
b101 '
b101 2
b1000 &
b1000 5
b1000 /
b1101 0
b11 8
b100 =
b101 <
b1000 ;
#17000
b1010 $
b1010 :
b1101 1
b0 9
b1010 3
b110 6
1*
b1010 ,
b101 .
b101 7
b1101 '
b1101 2
b1101 &
b1101 5
b1101 /
b11010 0
b0 8
b101 =
b1101 <
b1101 ;
#18000
0#
b1101 $
b1101 :
b10 1
b1011 4
b1001 9
b110 3
b1 6
1*
b1101 ,
b0 .
b0 7
b1010 '
b1010 2
b11 &
b11 5
b11 /
b1101 0
b11001 8
b0 =
b1010 <
b11 ;
#19000
0"
1%
b0 $
b0 :
b0 1
b1010 4
b1010 9
b0 3
b0 6
1-
0*
b0 ,
b101 .
b101 7
b0 &
b0 5
b0 /
b1010 0
b10110 8
b101 =
b0 ;
#20000
1"
0%
b1100 $
b1100 :
b10 1
b111 4
b101 9
b1100 3
b11 6
1*
b1100 ,
0-
b11 '
b11 2
b110 &
b110 5
b110 /
b1001 0
b11 8
b11 <
b110 ;
#21000
0"
b110 $
b110 :
b11 1
b1011 4
b1000 9
b110 3
b1 6
0*
b110 ,
b1011 '
b1011 2
b11 &
b11 5
b11 /
b1110 0
b11000 8
b1011 <
b11 ;
#22000
b100 $
b100 :
b10 1
b1110 4
b1100 9
b100 3
b100 ,
b1110 '
b1110 2
b10 &
b10 5
b10 /
b10000 0
b10100 8
b1110 <
b10 ;
#23000
1"
b1111 $
b1111 :
b11 1
b1111 4
b1110 3
b111 6
1*
b1111 ,
b10 .
b10 7
b11 '
b11 2
b1111 &
b1111 5
b1111 /
b10010 0
b1100 8
b10 =
b11 <
b1111 ;
#24000
b1110 $
b1110 :
b1000 1
b1110 4
b110 9
b100 3
b101 6
1*
b1110 ,
b1100 '
b1100 2
b1010 &
b1010 5
b1010 /
b10110 0
b11110 8
b1100 <
b1010 ;
#25000
b1011 $
b1011 :
b0 1
b1011 4
b1011 9
1*
b1011 ,
b0 .
b0 7
b1 '
b1 2
b1011 0
b1001 8
b0 =
b1 <
#26000
1"
0%
b1000 $
b1000 :
b1000 1
b1001 4
b1 9
b0 3
b100 6
1*
b1000 ,
b11 .
b11 7
b1001 '
b1001 2
b1000 &
b1000 5
b1000 /
b10001 0
b11111 8
b11 =
b1001 <
b1000 ;
#27000
0"
0%
b11 $
b11 :
b110 1
b110 4
b0 9
b1100 3
b11 6
0*
b11 ,
b110 .
b110 7
b110 '
b110 2
b110 &
b110 5
b110 /
b1100 0
b0 8
b110 =
b110 <
b110 ;
#28000
1"
b1000 $
b1000 :
b1000 1
b1110 4
b110 9
b1000 3
b110 6
1*
b1000 ,
b11 .
b11 7
b1010 '
b1010 2
b1100 &
b1100 5
b1100 /
b10110 0
b10 8
b11 =
b1010 <
b1100 ;
#29000
0"
0%
b1 $
b1 :
b1 1
b101 4
b100 9
b10 3
b0 6
0*
b1 ,
b111 .
b111 7
b101 '
b101 2
b1 &
b1 5
b1 /
b110 0
b11100 8
b111 =
b101 <
b1 ;
#30000
b101 $
b101 :
b1010 1
b1011 4
b1 9
b110 3
b101 6
b101 ,
b110 .
b110 7
b1010 '
b1010 2
b1011 &
b1011 5
b1011 /
b10101 0
b1 8
b110 =
b1010 <
b1011 ;
#31000
b100 $
b100 :
b1 1
b101 4
b100 9
b1010 3
b10 6
b100 ,
b1 .
b1 7
b1 '
b1 2
b101 &
b101 5
b101 /
b110 0
b100 8
b1 =
b1 <
b101 ;
#32000
0%
b10 $
b10 :
b0 1
b1110 4
b1110 9
b100 3
b1 6
b10 ,
b111 .
b111 7
b1100 '
b1100 2
b10 &
b10 5
b10 /
b1110 0
b10110 8
b111 =
b1100 <
b10 ;
#33000
1"
b1111 $
b1111 :
b1000 1
b1111 4
b111 9
b1110 3
b111 6
1*
b1111 ,
b1000 '
b1000 2
b1111 &
b1111 5
b1111 /
b10111 0
b111 8
b1000 <
b1111 ;
#34000
b1100 $
b1100 :
b1100 1
b11 9
1*
b1100 ,
b11 .
b11 7
b1100 '
b1100 2
b11011 0
b11 8
b11 =
b1100 <
#35000
1#
0"
b10 $
b10 :
1!
b1001 1
b1001 4
b0 9
b10 3
b100 6
1+
1)
0*
b10 ,
b0 .
b0 7
b1001 '
b1001 2
b1001 &
b1001 5
b1001 /
b10010 0
b0 8
b0 =
b1001 <
b1001 ;
#36000
0%
b11 $
b11 :
0!
0#
b1 1
b111 4
b110 9
b1110 3
b11 6
0+
0)
b11 ,
b110 .
b110 7
b1 '
b1 2
b111 &
b111 5
b111 /
b1000 0
b110 8
b110 =
b1 <
b111 ;
#37000
0#
1"
b1110 $
b1110 :
b0 1
b1110 4
b1110 9
b1000 3
b110 6
1*
b1110 ,
b0 .
b0 7
b10 '
b10 2
b1100 &
b1100 5
b1100 /
b1110 0
b1010 8
b0 =
b10 <
b1100 ;
#38000
1"
0%
b1111 $
b1111 :
b101 1
b1111 4
b1010 9
b1110 3
b11 6
1*
b1111 ,
b10 .
b10 7
b1101 '
b1101 2
b111 &
b111 5
b111 /
b10100 0
b11010 8
b10 =
b1101 <
b111 ;
#39000
0"
b1 $
b1 :
0#
b1100 1
b11 9
b1100 3
b111 6
0*
b1 ,
b1 .
b1 7
b1110 &
b1110 5
b1110 /
b11011 0
b1 8
b1 =
b1110 ;
#40000
1"
0%
b1110 $
b1110 :
b11 1
b1100 9
b1110 3
1*
b1110 ,
b101 .
b101 7
b11 '
b11 2
b1111 &
b1111 5
b1111 /
b10010 0
b1100 8
b101 =
b11 <
b1111 ;
#41000
b1101 $
b1101 :
1!
b1000 1
b1011 4
b11 9
b0 3
b100 6
1)
1*
b1101 ,
b1 .
b1 7
b1011 '
b1011 2
b1000 &
b1000 5
b1000 /
b10011 0
b11101 8
b1 =
b1011 <
b1000 ;
#42000
b1001 $
b1001 :
b1010 1
b1111 4
b101 9
b1110 3
b111 6
1*
1)
b1001 ,
b0 .
b0 7
b1010 '
b1010 2
b1111 &
b1111 5
b1111 /
b11001 0
b101 8
b0 =
b1010 <
b1111 ;
#43000
1"
0%
b1000 $
b1000 :
0!
b110 1
b1110 4
b1000 9
b1100 3
b11 6
1*
0)
b1000 ,
b100 .
b100 7
b1110 '
b1110 2
b110 &
b110 5
b110 /
b10100 0
b11000 8
b100 =
b1110 <
b110 ;
#44000
0"
b10 $
b10 :
b10 1
b1100 9
b100 3
b101 6
0*
b10 ,
b11 .
b11 7
b110 '
b110 2
b1010 &
b1010 5
b1010 /
b10000 0
b100 8
b11 =
b110 <
b1010 ;
#45000
b11 $
b11 :
b11 1
b1111 4
b110 3
b1 6
b11 ,
b1111 '
b1111 2
b11 &
b11 5
b11 /
b10010 0
b10100 8
b1111 <
b11 ;
#46000
1"
0%
b1111 $
b1111 :
b100 1
b1011 9
b1110 3
b111 6
1*
b1111 ,
b111 .
b111 7
b100 '
b100 2
b1111 &
b1111 5
b1111 /
b10011 0
b1011 8
b111 =
b100 <
b1111 ;
#47000
b10 1
b1101 9
b110 3
b101 6
1*
b1111 ,
b10 .
b10 7
b110 '
b110 2
b1011 &
b1011 5
b1011 /
b10001 0
b101 8
b10 =
b110 <
b1011 ;
#48000
b1101 $
b1101 :
b1001 1
b1101 4
b100 9
b10 3
b100 6
1*
b1101 ,
b1101 '
b1101 2
b1001 &
b1001 5
b1001 /
b10110 0
b11100 8
b1101 <
b1001 ;
#49000
0"
0%
b101 $
b101 :
b101 1
b101 4
b0 9
b1010 3
b10 6
0*
b101 ,
b111 .
b111 7
b101 '
b101 2
b101 &
b101 5
b101 /
b1010 0
b0 8
b111 =
b101 <
b101 ;
#50000
0#
1"
b1101 $
b1101 :
b0 1
b1101 4
b1101 9
b10 3
b100 6
1*
b1101 ,
b0 .
b0 7
b100 '
b100 2
b1001 &
b1001 5
b1001 /
b1101 0
b101 8
b0 =
b100 <
b1001 ;
#51000
0"
0%
b101 $
b101 :
b1010 1
b1011 4
b1 9
b100 3
b101 6
0*
b101 ,
b110 .
b110 7
b1011 '
b1011 2
b1010 &
b1010 5
b1010 /
b10101 0
b11111 8
b110 =
b1011 <
b1010 ;
#52000
1"
b1000 $
b1000 :
b1000 1
b1110 4
b110 9
b1000 3
b110 6
1*
b1000 ,
b101 .
b101 7
b1010 '
b1010 2
b1100 &
b1100 5
b1100 /
b10110 0
b10 8
b101 =
b1010 <
b1100 ;
#53000
0"
b1 $
b1 :
b10 1
b111 4
b101 9
b110 3
b1 6
0*
b1 ,
b110 .
b110 7
b110 '
b110 2
b11 &
b11 5
b11 /
b1001 0
b11101 8
b110 =
b110 <
b11 ;
#54000
b11 $
b11 :
b1111 4
b1101 9
b1110 3
b11 6
b11 ,
b1010 '
b1010 2
b111 &
b111 5
b111 /
b10001 0
b11101 8
b1010 <
b111 ;
#55000
1#
b1 $
b1 :
1!
b1000 1
b1001 4
b1 9
b0 3
b100 6
1+
1)
b1 ,
b0 .
b0 7
b1001 '
b1001 2
b1000 &
b1000 5
b1000 /
b10001 0
b11111 8
b0 =
b1001 <
b1000 ;
#56000
0%
b111 $
b111 :
0!
0#
b0 1
b111 4
b111 9
b1000 3
b10 6
0+
0)
b111 ,
b100 .
b100 7
b11 '
b11 2
b100 &
b100 5
b100 /
b111 0
b1 8
b100 =
b11 <
b100 ;
#57000
b10 $
b10 :
b1001 1
b1011 4
b10 9
b10 3
b100 6
b10 ,
b101 .
b101 7
b1011 '
b1011 2
b1001 &
b1001 5
b1001 /
b10100 0
b11110 8
b101 =
b1011 <
b1001 ;
#58000
b100 $
b100 :
b1101 4
b100 9
b100 ,
b110 .
b110 7
b1101 '
b1101 2
b10110 0
b11100 8
b110 =
b1101 <
#59000
b10 1
b1110 4
b1100 9
b100 3
b101 6
b100 ,
b101 .
b101 7
b110 '
b110 2
b1010 &
b1010 5
b1010 /
b10000 0
b100 8
b101 =
b110 <
b1010 ;
#60000
0%
b110 $
b110 :
b100 1
b110 4
b10 9
b1100 3
b11 6
b110 ,
b111 .
b111 7
b100 '
b100 2
b110 &
b110 5
b110 /
b1010 0
b10 8
b111 =
b100 <
b110 ;
#61000
0#
1"
b1101 $
b1101 :
b0 1
b1101 4
b1101 9
b10 3
b100 6
1*
b1101 ,
b0 .
b0 7
b1001 &
b1001 5
b1001 /
b1101 0
b101 8
b0 =
b1001 ;
#62000
1"
0%
b1000 $
b1000 :
b1000 1
b101 9
b0 3
1*
b1000 ,
b111 .
b111 7
b1101 '
b1101 2
b1000 &
b1000 5
b1000 /
b10101 0
b11011 8
b111 =
b1101 <
b1000 ;
#63000
0"
b110 $
b110 :
b1110 4
b110 9
b1100 3
b111 6
0*
b110 ,
b100 .
b100 7
b1000 '
b1000 2
b1110 &
b1110 5
b1110 /
b10110 0
b110 8
b100 =
b1000 <
b1110 ;
#64000
b100 $
b100 :
b1001 1
b1101 4
b100 9
b1010 3
b110 6
b100 ,
b1001 '
b1001 2
b1101 &
b1101 5
b1101 /
b10110 0
b100 8
b1001 <
b1101 ;
#65000
1"
b1100 $
b1100 :
b10 1
b1110 4
b1100 9
b1100 3
b11 6
1*
b1100 ,
b101 .
b101 7
b1010 '
b1010 2
b110 &
b110 5
b110 /
b10000 0
b11100 8
b101 =
b1010 <
b110 ;
#66000
0"
1%
b0 $
b0 :
b0 1
b110 4
b110 9
1-
0*
b0 ,
b11 .
b11 7
b0 '
b0 2
b110 0
b110 8
b11 =
b0 <
#67000
1"
0%
b1110 $
b1110 :
b1010 1
b1110 4
b100 9
b100 3
b101 6
1*
b1110 ,
0-
b10 .
b10 7
b1110 '
b1110 2
b1010 &
b1010 5
b1010 /
b11000 0
b11100 8
b10 =
b1110 <
b1010 ;
#68000
1#
b1011 $
b1011 :
1!
b0 1
b1111 4
b1111 9
b1010 3
b10 6
1+
1)
1*
b1011 ,
b1 .
b1 7
b1010 '
b1010 2
b101 &
b101 5
b101 /
b1111 0
b11011 8
b1 =
b1010 <
b101 ;
#69000
b1101 $
b1101 :
0!
1#
b110 1
b111 4
b1 9
b1110 3
b11 6
1+
1*
0)
b1101 ,
b0 .
b0 7
b110 '
b110 2
b111 &
b111 5
b111 /
b1101 0
b1 8
b0 =
b110 <
b111 ;
#70000
1"
0%
b1100 $
b1100 :
0#
b110 4
b0 9
b1100 3
0+
1*
b1100 ,
b101 .
b101 7
b110 &
b110 5
b110 /
b1100 0
b0 8
b101 =
b110 ;
#71000
0"
b10 $
b10 :
1!
0#
b100 1
b1110 4
b1010 9
b1000 3
b110 6
1)
0*
b10 ,
b0 .
b0 7
b1100 &
b1100 5
b1100 /
b10010 0
b110 8
b0 =
b1100 ;
#72000
1"
0%
b1110 $
b1110 :
0!
b1010 1
b1111 4
b101 9
b1100 3
b111 6
1*
0)
b1110 ,
b111 .
b111 7
b1011 '
b1011 2
b1110 &
b1110 5
b1110 /
b11001 0
b11 8
b111 =
b1011 <
b1110 ;
#73000
b1111 $
b1111 :
1!
b1000 1
b1011 4
b11 9
b10 3
b100 6
1)
1*
b1111 ,
b1 .
b1 7
b1010 '
b1010 2
b1001 &
b1001 5
b1001 /
b10011 0
b11111 8
b1 =
b1010 <
b1001 ;
#74000
0"
0%
b11 $
b11 :
0!
b1 1
b111 4
b110 9
b1110 3
b11 6
0*
0)
b11 ,
b110 .
b110 7
b1 '
b1 2
b111 &
b111 5
b111 /
b1000 0
b110 8
b110 =
b1 <
b111 ;
#75000
1%
b0 $
b0 :
b0 1
b101 4
b101 9
b0 3
b0 6
1-
b0 ,
b101 .
b101 7
b101 '
b101 2
b0 &
b0 5
b0 /
b101 0
b11011 8
b101 =
b101 <
b0 ;
#76000
0%
b10 $
b10 :
b1 1
b1001 4
b1000 9
b10 3
b100 6
b10 ,
0-
b1 '
b1 2
b1001 &
b1001 5
b1001 /
b1010 0
b1000 8
b1 <
b1001 ;
#77000
1"
b1000 $
b1000 :
b1000 1
b1011 4
b11 9
b0 3
1*
b1000 ,
b11 .
b11 7
b1011 '
b1011 2
b1000 &
b1000 5
b1000 /
b10011 0
b11101 8
b11 =
b1011 <
b1000 ;
#78000
0"
0%
b110 $
b110 :
b1110 4
b110 9
b1000 3
b110 6
0*
b110 ,
b110 .
b110 7
b1010 '
b1010 2
b1100 &
b1100 5
b1100 /
b10110 0
b10 8
b110 =
b1010 <
b1100 ;
#79000
1"
b1111 $
b1111 :
1!
b1001 4
b1 9
b0 3
b100 6
1*
1)
b1111 ,
b1 .
b1 7
b1001 '
b1001 2
b1000 &
b1000 5
b1000 /
b10001 0
b11111 8
b1 =
b1001 <
b1000 ;
#80000
1"
0%
b1110 $
b1110 :
0!
b110 1
b1110 4
b1000 9
b1100 3
b111 6
1*
0)
b1110 ,
b111 .
b111 7
b110 '
b110 2
b1110 &
b1110 5
b1110 /
b10100 0
b1000 8
b111 =
b110 <
b1110 ;
#81000
0"
b100 $
b100 :
b1010 1
b1010 4
b0 9
b100 3
b101 6
0*
b100 ,
b101 .
b101 7
b1010 '
b1010 2
b1010 &
b1010 5
b1010 /
b10100 0
b0 8
b101 =
b1010 <
b1010 ;
#82000
b110 $
b110 :
b1000 1
b1110 4
b110 9
b1100 3
b111 6
b110 ,
b1 .
b1 7
b1000 '
b1000 2
b1110 &
b1110 5
b1110 /
b10110 0
b110 8
b1 =
b1000 <
b1110 ;
#83000
1"
0%
b1000 $
b1000 :
b1010 4
b10 9
b0 3
b100 6
1*
b1000 ,
b11 .
b11 7
b1010 '
b1010 2
b1000 &
b1000 5
b1000 /
b10010 0
b11110 8
b11 =
b1010 <
b1000 ;
#84000
0"
0%
b101 $
b101 :
b11 1
b1111 4
b1100 9
b110 3
b101 6
0*
b101 ,
b110 .
b110 7
b111 '
b111 2
b1011 &
b1011 5
b1011 /
b10010 0
b100 8
b110 =
b111 <
b1011 ;
#85000
b110 $
b110 :
1#
b0 1
b1110 4
b1110 9
b100 3
1+
b110 ,
b1 .
b1 7
b100 '
b100 2
b1010 &
b1010 5
b1010 /
b1110 0
b110 8
b1 =
b100 <
b1010 ;
#86000
0%
b10 $
b10 :
0#
b110 4
b110 9
b1 6
0+
b10 ,
b111 .
b111 7
b10 &
b10 5
b10 /
b110 0
b11110 8
b111 =
b10 ;
#87000
1"
b1110 $
b1110 :
b10 1
b1110 4
b1100 9
b1100 3
b11 6
1*
b1110 ,
b10 .
b10 7
b1010 '
b1010 2
b110 &
b110 5
b110 /
b10000 0
b11100 8
b10 =
b1010 <
b110 ;
#88000
1"
0%
b1111 $
b1111 :
b0 1
b1111 4
b1111 9
b100 3
b1 6
1*
b1111 ,
b100 .
b100 7
b1101 '
b1101 2
b10 &
b10 5
b10 /
b1111 0
b10101 8
b100 =
b1101 <
b10 ;
#89000
b1010 $
b1010 :
1!
1#
b1110 4
b1110 9
b1000 3
b10 6
1+
1)
1*
b1010 ,
b1 .
b1 7
b1010 '
b1010 2
b100 &
b100 5
b100 /
b1110 0
b11010 8
b1 =
b1010 <
b100 ;
#90000
0"
1%
b0 $
b0 :
0!
0#
b1111 4
b1111 9
b10 3
b0 6
1-
0+
0*
0)
b0 ,
b11 .
b11 7
b1110 '
b1110 2
b1 &
b1 5
b1 /
b1111 0
b10011 8
b11 =
b1110 <
b1 ;
#91000
1"
0%
b1100 $
b1100 :
1!
b1011 1
b100 9
b110 3
b101 6
1*
1)
b1100 ,
0-
b1 .
b1 7
b1111 '
b1111 2
b1011 &
b1011 5
b1011 /
b11010 0
b11100 8
b1 =
b1111 <
b1011 ;
#92000
0"
0%
b110 $
b110 :
0!
b100 1
b111 4
b11 9
b1100 3
b11 6
0*
0)
b110 ,
b111 .
b111 7
b101 '
b101 2
b110 &
b110 5
b110 /
b1011 0
b1 8
b111 =
b101 <
b110 ;
#93000
b101 $
b101 :
b1000 1
b1011 4
b110 3
b101 6
b101 ,
b110 .
b110 7
b1000 '
b1000 2
b1011 &
b1011 5
b1011 /
b10011 0
b11 8
b110 =
b1000 <
b1011 ;
#94000
1"
b1101 $
b1101 :
0#
b10 1
b1001 9
1*
b1101 ,
b0 .
b0 7
b10 '
b10 2
b1101 0
b1001 8
b0 =
b10 <
